{
  "topic": "Bar Graphs",
  "level": "Medium",
  "questions": [
    {
      "id": 1,
      "question": "An intermediate question about Bar Graphs?",
      "options": [
        "Option A",
        "Option B",
        "Option C",
        "Option D"
      ],
      "correct_option": "Option A",
      "explanation": "This is a sample medium level question for Bar Graphs. Replace with actual questions."
    },
    {
      "id": 2,
      "question": "Which statement is true regarding Bar Graphs?",
      "options": [
        "Option A",
        "Option B",
        "Option C",
        "Option D"
      ],
      "correct_option": "Option A",
      "explanation": "This is a sample medium level question for Bar Graphs. Replace with actual questions."
    },
    {
      "id": 3,
      "question": "A moderate difficulty problem in Bar Graphs?",
      "options": [
        "Option A",
        "Option B",
        "Option C",
        "Option D"
      ],
      "correct_option": "Option A",
      "explanation": "This is a sample medium level question for Bar Graphs. Replace with actual questions."
    },
    {
      "id": 4,
      "question": "Application of intermediate Bar Graphs concepts?",
      "options": [
        "Option A",
        "Option B",
        "Option C",
        "Option D"
      ],
      "correct_option": "Option A",
      "explanation": "This is a sample medium level question for Bar Graphs. Replace with actual questions."
    },
    {
      "id": 5,
      "question": "A more complex Bar Graphs scenario?",
      "options": [
        "Option A",
        "Option B",
        "Option C",
        "Option D"
      ],
      "correct_option": "Option A",
      "explanation": "This is a sample medium level question for Bar Graphs. Replace with actual questions."
    }
  ]
}