{
  "topic": "Statement-Arguments",
  "level": "Medium",
  "questions": [
    {
      "id": 1,
      "question": "An intermediate question about Statement-Arguments?",
      "options": [
        "Option A",
        "Option B",
        "Option C",
        "Option D"
      ],
      "correct_option": "Option A",
      "explanation": "This is a sample medium level question for Statement-Arguments. Replace with actual questions."
    },
    {
      "id": 2,
      "question": "Which statement is true regarding Statement-Arguments?",
      "options": [
        "Option A",
        "Option B",
        "Option C",
        "Option D"
      ],
      "correct_option": "Option A",
      "explanation": "This is a sample medium level question for Statement-Arguments. Replace with actual questions."
    },
    {
      "id": 3,
      "question": "A moderate difficulty problem in Statement-Arguments?",
      "options": [
        "Option A",
        "Option B",
        "Option C",
        "Option D"
      ],
      "correct_option": "Option A",
      "explanation": "This is a sample medium level question for Statement-Arguments. Replace with actual questions."
    },
    {
      "id": 4,
      "question": "Application of intermediate Statement-Arguments concepts?",
      "options": [
        "Option A",
        "Option B",
        "Option C",
        "Option D"
      ],
      "correct_option": "Option A",
      "explanation": "This is a sample medium level question for Statement-Arguments. Replace with actual questions."
    },
    {
      "id": 5,
      "question": "A more complex Statement-Arguments scenario?",
      "options": [
        "Option A",
        "Option B",
        "Option C",
        "Option D"
      ],
      "correct_option": "Option A",
      "explanation": "This is a sample medium level question for Statement-Arguments. Replace with actual questions."
    }
  ]
}